kick/__init__.py
kick/version.py
kick/device2/__init__.py
kick/device2/asa/__init__.py
kick/device2/asa/actions/__init__.py
kick/device2/asa/actions/asa.py
kick/device2/asa/actions/asa_cluster.py
kick/device2/asa/actions/asa_config.py
kick/device2/asa/actions/asa_diameter.py
kick/device2/asa/actions/asa_gtp.py
kick/device2/asa/actions/asa_ha.py
kick/device2/asa/actions/constants.py
kick/device2/asa/actions/dialogs.py
kick/device2/asa/actions/patterns.py
kick/device2/asa/actions/statemachine.py
kick/device2/asa/actions/statements.py
kick/device2/chassis/__init__.py
kick/device2/chassis/actions/__init__.py
kick/device2/chassis/actions/chassis.py
kick/device2/chassis/actions/dialogs.py
kick/device2/chassis/actions/patterns.py
kick/device2/chassis/actions/statemachine.py
kick/device2/chassis/actions/statements.py
kick/device2/elektra/__init__.py
kick/device2/elektra/actions/__init__.py
kick/device2/elektra/actions/constants.py
kick/device2/elektra/actions/dialogs.py
kick/device2/elektra/actions/elektra.py
kick/device2/elektra/actions/patterns.py
kick/device2/elektra/actions/statemachine.py
kick/device2/elektra/actions/statements.py
kick/device2/elektra5585/__init__.py
kick/device2/elektra5585/actions/__init__.py
kick/device2/elektra5585/actions/constants.py
kick/device2/elektra5585/actions/dialogs.py
kick/device2/elektra5585/actions/elektra5585.py
kick/device2/elektra5585/actions/patterns.py
kick/device2/elektra5585/actions/statemachine.py
kick/device2/elektra5585/actions/statements.py
kick/device2/ep/__init__.py
kick/device2/ep/actions/__init__.py
kick/device2/ep/actions/dialogs.py
kick/device2/ep/actions/ep.py
kick/device2/ep/actions/patterns.py
kick/device2/ep/actions/statemachine.py
kick/device2/ep/actions/statements.py
kick/device2/fmc/__init__.py
kick/device2/fmc/actions/__init__.py
kick/device2/fmc/actions/dialogs.py
kick/device2/fmc/actions/fmc.py
kick/device2/fmc/actions/patterns.py
kick/device2/fmc/actions/statemachine.py
firepower_kickstart-0.2.1.dist-info/LICENSE
firepower_kickstart-0.2.1.dist-info/METADATA
firepower_kickstart-0.2.1.dist-info/WHEEL
firepower_kickstart-0.2.1.dist-info/top_level.txt
firepower_kickstart-0.2.1.dist-info/RECORD
