Metadata-Version: 2.1
Name: firepower-kickstart
Version: 0.2.1
Summary: Python modules to install Firepower Threat Defense images (FTD) on hardware platforms.
Home-page: https://github.com/CiscoDevNet/firepower-kickstart
Author: Cisco Systems Inc.
Author-email: firepower-kickstart-support-ext@cisco.com
License: UNKNOWN
Platform: UNKNOWN
Classifier: Programming Language :: Python :: 3 :: Only
Classifier: Programming Language :: Python :: Implementation :: CPython
Classifier: License :: OSI Approved :: Apache Software License
Classifier: Operating System :: POSIX :: Linux
Requires-Dist: pyVmomi
Requires-Dist: paramiko
Requires-Dist: unicon
Requires-Dist: boto3
Requires-Dist: munch
Requires-Dist: beautifulsoup4
Requires-Dist: Fabric3
